lib_version_team11.py
lib_version_team11-0.0.1.dist-info/METADATA
lib_version_team11-0.0.1.dist-info/WHEEL
lib_version_team11-0.0.1.dist-info/RECORD
